gabposter/__init__.py
gabposter/gab_driver.py
gabposter/version.py
gabposter-1.2.8.dist-info/LICENSE
gabposter-1.2.8.dist-info/METADATA
gabposter-1.2.8.dist-info/WHEEL
gabposter-1.2.8.dist-info/top_level.txt
gabposter-1.2.8.dist-info/RECORD
