Metadata-Version: 2.1
Name: gabposter
Version: 1.2.8
Summary: Selenium driver that posts to gab.
Home-page: https://github.com/zackees/gabposter
Author: Zach Vorhies
Author-email: dont@email.me
License: MIT
Platform: UNKNOWN
Classifier: License :: OSI Approved :: MIT License
Classifier: Programming Language :: Python :: 3.6
Classifier: Programming Language :: Python :: 3.9
Classifier: Operating System :: Microsoft :: Windows
Classifier: Operating System :: POSIX
Classifier: Operating System :: MacOS :: MacOS X
Classifier: Environment :: Console
Requires-Python: >=3.6.0
Requires-Dist: open-webdriver (>=1.3.0)
Requires-Dist: pyjpgclipboard (>=1.0.2)
Requires-Dist: download
Provides-Extra: test
Requires-Dist: pytest ; extra == 'test'
